odoo/addons/edi_queue_oca/README.rst
odoo/addons/edi_queue_oca/__init__.py
odoo/addons/edi_queue_oca/__manifest__.py
odoo/addons/edi_queue_oca/utils.py
odoo/addons/edi_queue_oca/data/job_channel.xml
odoo/addons/edi_queue_oca/data/job_function.xml
odoo/addons/edi_queue_oca/i18n/edi_queue_oca.pot
odoo/addons/edi_queue_oca/i18n/it.po
odoo/addons/edi_queue_oca/models/__init__.py
odoo/addons/edi_queue_oca/models/edi_backend.py
odoo/addons/edi_queue_oca/models/edi_exchange_record.py
odoo/addons/edi_queue_oca/models/edi_exchange_type.py
odoo/addons/edi_queue_oca/readme/CONTRIBUTORS.md
odoo/addons/edi_queue_oca/readme/DESCRIPTION.md
odoo/addons/edi_queue_oca/security/ir_model_access.xml
odoo/addons/edi_queue_oca/static/description/icon.png
odoo/addons/edi_queue_oca/static/description/index.html
odoo/addons/edi_queue_oca/tests/__init__.py
odoo/addons/edi_queue_oca/tests/test_backend_jobs.py
odoo/addons/edi_queue_oca/tests/test_backend_output_jobs.py
odoo/addons/edi_queue_oca/tests/test_record.py
odoo/addons/edi_queue_oca/views/edi_exchange_record.xml
odoo/addons/edi_queue_oca/views/edi_exchange_type.xml
odoo_addon_edi_queue_oca-18.0.1.0.1.2.dist-info/METADATA
odoo_addon_edi_queue_oca-18.0.1.0.1.2.dist-info/WHEEL
odoo_addon_edi_queue_oca-18.0.1.0.1.2.dist-info/top_level.txt
odoo_addon_edi_queue_oca-18.0.1.0.1.2.dist-info/RECORD
